md_citeproc/__init__.py
md_citeproc/exceptions.py
md_citeproc/extension.py
md_citeproc/utils.py
md_citeproc/assets/__init__.py
md_citeproc/assets/binary/__init__.py
md_citeproc/assets/binary/citeproc-cli-linux
md_citeproc/assets/binary/citeproc-cli-macos
md_citeproc/assets/binary/citeproc-cli-win.exe
md_citeproc/assets/locales/__init__.py
md_citeproc/assets/locales/locales-af-ZA.xml
md_citeproc/assets/locales/locales-ar.xml
md_citeproc/assets/locales/locales-bg-BG.xml
md_citeproc/assets/locales/locales-ca-AD.xml
md_citeproc/assets/locales/locales-cs-CZ.xml
md_citeproc/assets/locales/locales-cy-GB.xml
md_citeproc/assets/locales/locales-da-DK.xml
md_citeproc/assets/locales/locales-de-AT.xml
md_citeproc/assets/locales/locales-de-CH.xml
md_citeproc/assets/locales/locales-de-DE.xml
md_citeproc/assets/locales/locales-el-GR.xml
md_citeproc/assets/locales/locales-en-GB.xml
md_citeproc/assets/locales/locales-en-US.xml
md_citeproc/assets/locales/locales-es-CL.xml
md_citeproc/assets/locales/locales-es-ES.xml
md_citeproc/assets/locales/locales-es-MX.xml
md_citeproc/assets/locales/locales-et-EE.xml
md_citeproc/assets/locales/locales-eu.xml
md_citeproc/assets/locales/locales-fa-IR.xml
md_citeproc/assets/locales/locales-fi-FI.xml
md_citeproc/assets/locales/locales-fr-CA.xml
md_citeproc/assets/locales/locales-fr-FR.xml
md_citeproc/assets/locales/locales-he-IL.xml
md_citeproc/assets/locales/locales-hi-IN.xml
md_citeproc/assets/locales/locales-hr-HR.xml
md_citeproc/assets/locales/locales-hu-HU.xml
md_citeproc/assets/locales/locales-id-ID.xml
md_citeproc/assets/locales/locales-is-IS.xml
md_citeproc/assets/locales/locales-it-IT.xml
md_citeproc/assets/locales/locales-ja-JP.xml
md_citeproc/assets/locales/locales-km-KH.xml
md_citeproc/assets/locales/locales-ko-KR.xml
md_citeproc/assets/locales/locales-la.xml
md_citeproc/assets/locales/locales-lt-LT.xml
md_citeproc/assets/locales/locales-lv-LV.xml
md_citeproc/assets/locales/locales-mn-MN.xml
md_citeproc/assets/locales/locales-nb-NO.xml
md_citeproc-0.2.2.dist-info/LICENSE.txt
md_citeproc-0.2.2.dist-info/METADATA
md_citeproc-0.2.2.dist-info/WHEEL
md_citeproc-0.2.2.dist-info/top_level.txt
md_citeproc-0.2.2.dist-info/RECORD
