Metadata-Version: 2.1
Name: md-citeproc
Version: 0.2.2
Summary: Citeproc extension for Python-Markdown
Home-page: https://md-citeproc.readthedocs.io
Author: Martin Obrist
Author-email: dev@obrist.email
License: GPLv3
Project-URL: Documentation, https://md-citeproc.readthedocs.io
Project-URL: Source Code, https://gitlab.com/dinuthehuman/md_citeproc
Project-URL: Issue Tracker, https://gitlab.com/dinuthehuman/md_citeproc/-/issues
Keywords: markdown,citeproc
Platform: UNKNOWN
Classifier: Development Status :: 3 - Alpha
Classifier: Topic :: Text Processing :: Markup :: Markdown
Classifier: License :: OSI Approved :: GNU General Public License v3 (GPLv3)
Classifier: Operating System :: OS Independent
Classifier: Programming Language :: Python :: 3
Classifier: Programming Language :: Python :: 3.9
Classifier: Programming Language :: Python :: 3.10
Classifier: Programming Language :: Python :: 3 :: Only
Requires-Python: >=3.9, <4
License-File: LICENSE.txt
Requires-Dist: jinja2
Requires-Dist: Markdown
Provides-Extra: dev
Requires-Dist: gitpython ; extra == 'dev'
Requires-Dist: mkdocs ; extra == 'dev'
Requires-Dist: mkdocstrings ; extra == 'dev'
Requires-Dist: twine ; extra == 'dev'
Requires-Dist: pytest ; extra == 'dev'
Requires-Dist: nose ; extra == 'dev'
Requires-Dist: invoke ; extra == 'dev'
